react_table_dash/ReactTableDash.py
react_table_dash/__init__.py
react_table_dash/_imports_.py
react_table_dash/metadata.json
react_table_dash/package-info.json
react_table_dash/react_table_dash.min.js
react_table_dash/react_table_dash.min.js.map
react_table_dash-0.0.3.dist-info/LICENSE
react_table_dash-0.0.3.dist-info/METADATA
react_table_dash-0.0.3.dist-info/WHEEL
react_table_dash-0.0.3.dist-info/top_level.txt
react_table_dash-0.0.3.dist-info/RECORD
