Metadata-Version: 2.1
Name: react-table-dash
Version: 0.0.3
Summary: Dash component based on React Table v6
Home-page: UNKNOWN
Author: Mauri Larikka <mauri.larikka@gmail.com>
License: MIT
Platform: UNKNOWN
Classifier: Framework :: Dash
